LICENSE
MANIFEST.in
README.md
setup.cfg
setup.py
tap_closeio/__init__.py
tap_closeio/context.py
tap_closeio/http.py
tap_closeio/schemas.py
tap_closeio/streams.py
tap_closeio/transform.py
tap_closeio.egg-info/PKG-INFO
tap_closeio.egg-info/SOURCES.txt
tap_closeio.egg-info/dependency_links.txt
tap_closeio.egg-info/entry_points.txt
tap_closeio.egg-info/requires.txt
tap_closeio.egg-info/top_level.txt
tap_closeio/schemas/activities.json
tap_closeio/schemas/custom_fields.json
tap_closeio/schemas/event_log.json
tap_closeio/schemas/integration_links.json
tap_closeio/schemas/leads.json
tap_closeio/schemas/tasks.json
tap_closeio/schemas/users.json