Metadata-Version: 1.1
Name: tap-closeio
Version: 1.5.1
Summary: Singer.io tap for extracting data from the CloseIO API
Home-page: http://singer.io
Author: Stitch
Author-email: UNKNOWN
License: UNKNOWN
Platform: UNKNOWN
Classifier: Programming Language :: Python :: 3 :: Only
